lakeshore/__init__.py
lakeshore/em_power_supply.py
lakeshore/fast_hall_controller.py
lakeshore/generic_instrument.py
lakeshore/model_121.py
lakeshore/model_155.py
lakeshore/model_224.py
lakeshore/model_224_enums.py
lakeshore/model_240.py
lakeshore/model_240_enums.py
lakeshore/model_335.py
lakeshore/model_335_enums.py
lakeshore/model_336.py
lakeshore/model_336_enums.py
lakeshore/model_350.py
lakeshore/model_372.py
lakeshore/model_372_enums.py
lakeshore/model_425.py
lakeshore/requires_firmware_version.py
lakeshore/ssm_base_module.py
lakeshore/ssm_measure_module.py
lakeshore/ssm_settings_profiles.py
lakeshore/ssm_source_module.py
lakeshore/ssm_system.py
lakeshore/ssm_system_enums.py
lakeshore/temperature_controllers.py
lakeshore/temperature_controllers_enums.py
lakeshore/teslameter.py
lakeshore/xip_instrument.py
lakeshore-1.9.2.dist-info/LICENSE
lakeshore-1.9.2.dist-info/METADATA
lakeshore-1.9.2.dist-info/WHEEL
lakeshore-1.9.2.dist-info/top_level.txt
lakeshore-1.9.2.dist-info/RECORD
