Metadata-Version: 2.1
Name: lakeshore
Version: 1.9.2
Summary: A package to connect to and interact with Lake Shore instruments.
Home-page: https://github.com/lakeshorecryotronics/python-driver
Maintainer: Lake Shore Cryotronics, Inc.
Maintainer-email: service@lakeshore.com
License: MIT
Platform: UNKNOWN
Classifier: Programming Language :: Python :: 3
Requires-Python: >=3.7
License-File: LICENSE
Requires-Dist: pyserial>=3.0
Requires-Dist: iso8601
Requires-Dist: packaging
Requires-Dist: wakepy>=0.7.1
Requires-Dist: enum34; python_version < "3.4"
